.gitignore
LICENSE
README.md
setup.cfg
setup.py
tox.ini
doc/login_flow.svg
doc/login_flow.txt
matrix_synapse_saml_mozilla/__init__.py
matrix_synapse_saml_mozilla/_sessions.py
matrix_synapse_saml_mozilla/mapping_provider.py
matrix_synapse_saml_mozilla/username_picker.py
matrix_synapse_saml_mozilla.egg-info/PKG-INFO
matrix_synapse_saml_mozilla.egg-info/SOURCES.txt
matrix_synapse_saml_mozilla.egg-info/dependency_links.txt
matrix_synapse_saml_mozilla.egg-info/requires.txt
matrix_synapse_saml_mozilla.egg-info/top_level.txt
matrix_synapse_saml_mozilla/res/index.html
matrix_synapse_saml_mozilla/res/script.js
matrix_synapse_saml_mozilla/res/style.css
tests/__init__.py
tests/test_attributes.py
tests/test_saml_response.xml