Metadata-Version: 2.1
Name: matrix-synapse-saml-mozilla
Version: 0.2.1
Summary: An Mozilla-flavoured SAML MXID mapper for Synapse
Home-page: UNKNOWN
License: UNKNOWN
Platform: UNKNOWN
Classifier: Development Status :: 4 - Beta
Classifier: License :: OSI Approved :: Apache Software License
Classifier: Programming Language :: Python :: 3
